crawliexpress/__init__.py
crawliexpress/category.py
crawliexpress/client.py
crawliexpress/exceptions.py
crawliexpress/feedback.py
crawliexpress/feedback_page.py
crawliexpress/item.py
crawliexpress/search.py
crawliexpress/search_page.py
crawliexpress-0.1.7.dist-info/LICENSE
crawliexpress-0.1.7.dist-info/METADATA
crawliexpress-0.1.7.dist-info/WHEEL
crawliexpress-0.1.7.dist-info/top_level.txt
crawliexpress-0.1.7.dist-info/RECORD
