Metadata-Version: 2.1
Name: crawliexpress
Version: 0.1.7
Summary: Python3 library to ease Aliexpress crawling
Home-page: https://github.com/toucantocard/crawliexpress
Author: ToucanTocard
Author-email: contact@robin.ninja
License: MIT
Keywords: aliexpress
Platform: UNKNOWN
Classifier: Development Status :: 4 - Beta
Classifier: Programming Language :: Python :: 3
Classifier: License :: OSI Approved :: MIT License
Classifier: Operating System :: OS Independent
Requires-Python: >=3.6
Requires-Dist: requests
Requires-Dist: jsonnet
Requires-Dist: bs4
Requires-Dist: lxml
Requires-Dist: sphinx-rtd-theme
Requires-Dist: sphinx-markdown-builder
